LICENSE
README.md
setup.py
SiderealKundliCraft/AstroChart.py
SiderealKundliCraft/SiderealAstroData.py
SiderealKundliCraft/__init__.py
SiderealKundliCraft.egg-info/PKG-INFO
SiderealKundliCraft.egg-info/SOURCES.txt
SiderealKundliCraft.egg-info/dependency_links.txt
SiderealKundliCraft.egg-info/requires.txt
SiderealKundliCraft.egg-info/top_level.txt
SiderealKundliCraft/tools/JulianDate.py
SiderealKundliCraft/tools/__init__.py