Metadata-Version: 2.1
Name: SiderealKundliCraft
Version: 6.1.0
Summary: This Python package is for astrology.
Home-page: https://github.com/EH30/SiderealKundliCraft
Author: EH
License: Unlicense
Keywords: Astrology,Sidereal Astrology,Kundli,Sidereal,Tools,Chart
Classifier: Programming Language :: Python :: 3.6
Classifier: License :: Freely Distributable
Classifier: Operating System :: OS Independent
Classifier: Development Status :: 5 - Production/Stable
Classifier: Environment :: Other Environment
Classifier: Intended Audience :: Developers
Classifier: Intended Audience :: Science/Research
Classifier: Topic :: Software Development :: Libraries :: Python Modules
License-File: LICENSE
